unlocknn/__init__.py
unlocknn/download.py
unlocknn/initializers.py
unlocknn/kernel_layers.py
unlocknn/megnet_utils.py
unlocknn/metrics.py
unlocknn/model.py
unlockNN-2.0.3.dist-info/LICENSE
unlockNN-2.0.3.dist-info/METADATA
unlockNN-2.0.3.dist-info/WHEEL
unlockNN-2.0.3.dist-info/top_level.txt
unlockNN-2.0.3.dist-info/RECORD
