Metadata-Version: 2.1
Name: unlockNN
Version: 2.0.3
Summary: Uncertainty quantification for neural network models of chemical systems.
Home-page: https://github.com/a-ws-m/unlockNN
Author: Alexander Moriarty
Author-email: amoriarty14@gmail.com
License: MIT
Keywords: keras,tensorflow,megnet,machine learning,uncertainty quantification
Classifier: Intended Audience :: Science/Research
Classifier: License :: OSI Approved :: MIT License
Classifier: Programming Language :: Python :: 3
Classifier: Programming Language :: Python :: 3.6
Classifier: Programming Language :: Python :: 3.7
Classifier: Programming Language :: Python :: 3.8
Classifier: Programming Language :: Python :: 3.9
Classifier: Topic :: Scientific/Engineering :: Artificial Intelligence
Classifier: Topic :: Scientific/Engineering :: Chemistry
Requires-Python: >=3.6
License-File: LICENSE
Requires-Dist: numpy (<=1.19.5)
Requires-Dist: pymatgen (<=2021.2.8)
Requires-Dist: megnet (>=1.1.4)
Requires-Dist: requests
Requires-Dist: pyarrow (>=1.0.1)
Requires-Dist: tensorflow (>=2.2)
Requires-Dist: tensorflow-probability (>=0.10.1)
Requires-Dist: typish ; python_version < "3.8"
Provides-Extra: compatible_matminer_version
Requires-Dist: matminer (==0.6.5) ; extra == 'compatible_matminer_version'
